{
    "Dialog": {
        "Window": {
            "Type": "Layout",
            "Name": "LotteryInfoItem",
            "Property": [
                {
                    "Name": "Area",
                    "Value": "{{0,0},{0,0},{1,0},{1,0}}"
                },
                {
                    "Name": "BackgroundColor",
                    "Value": "1 1 1 1"
                },
                {
                    "Name": "WndOpenSound",
                    "Value": "0"
                },
                {
                    "Name": "WndCloseSound",
                    "Value": "0"
                }
            ],
            "Window": [
                {
                    "Type": "StaticText",
                    "Name": "LotteryInfoItem-PrizeQuality",
                    "Property": [
                        {
                            "Name": "Area",
                            "Value": "{{0,0},{0,0},{0.17692,-3},{1,0}}"
                        },
                        {
                            "Name": "Text",
                            "Value": "品质"
                        },
                        {
                            "Name": "Touchable",
                            "Value": "false"
                        },
                        {
                            "Name": "WndOpenSound",
                            "Value": "0"
                        },
                        {
                            "Name": "WndCloseSound",
                            "Value": "0"
                        },
                        {
                            "Name": "TextColor",
                            "Value": "0.188235 0.172549 0.168627 1"
                        },
                        {
                            "Name": "TextHorzAlignment",
                            "Value": "Centre"
                        },
                        {
                            "Name": "TextLineExtraSpace",
                            "Value": "0"
                        },
                        {
                            "Name": "TextVertAlignment",
                            "Value": "Centre"
                        }
                    ]
                },
                {
                    "Type": "StaticText",
                    "Name": "LotteryInfoItem-PrizeName",
                    "Property": [
                        {
                            "Name": "Area",
                            "Value": "{{0.17692,3},{0,0},{0.75164,-3},{1,0}}"
                        },
                        {
                            "Name": "Text",
                            "Value": "奖品名称"
                        },
                        {
                            "Name": "Touchable",
                            "Value": "false"
                        },
                        {
                            "Name": "WndOpenSound",
                            "Value": "0"
                        },
                        {
                            "Name": "WndCloseSound",
                            "Value": "0"
                        },
                        {
                            "Name": "TextColor",
                            "Value": "0.188235 0.172549 0.168627 1"
                        },
                        {
                            "Name": "TextHorzAlignment",
                            "Value": "Centre"
                        },
                        {
                            "Name": "TextLineExtraSpace",
                            "Value": "0"
                        },
                        {
                            "Name": "TextVertAlignment",
                            "Value": "Centre"
                        }
                    ],
                    "Window": [
                        {
                            "Type": "StaticImage",
                            "Name": "LotteryInfoItem-IconBack",
                            "Property": [
                                {
                                    "Name": "Area",
                                    "Value": "{{0.05927,0},{0,0},{0.05927,74},{0,74}}"
                                },
                                {
                                    "Name": "VerticalAlignment",
                                    "Value": "Centre"
                                },
                                {
                                    "Name": "Touchable",
                                    "Value": "false"
                                },
                                {
                                    "Name": "WndOpenSound",
                                    "Value": "0"
                                },
                                {
                                    "Name": "WndCloseSound",
                                    "Value": "0"
                                },
                                {
                                    "Name": "HexgonOverlayerColor",
                                    "Value": "1 1 1 1"
                                },
                                {
                                    "Name": "HexgonOverlayerImage",
                                    "Value": ""
                                },
                                {
                                    "Name": "HexgonSideColor",
                                    "Value": "1 1 1 1"
                                },
                                {
                                    "Name": "HexgonSideImage",
                                    "Value": ""
                                },
                                {
                                    "Name": "HexgonTopColor",
                                    "Value": "1 1 1 1"
                                },
                                {
                                    "Name": "HexgonTopImage",
                                    "Value": ""
                                }
                            ],
                            "Window": [
                                {
                                    "Type": "StaticImage",
                                    "Name": "LotteryInfoItem-Icon",
                                    "Property": [
                                        {
                                            "Name": "Area",
                                            "Value": "{{0,0},{0,0},{1,-20},{1,-20}}"
                                        },
                                        {
                                            "Name": "VerticalAlignment",
                                            "Value": "Centre"
                                        },
                                        {
                                            "Name": "HorizontalAlignment",
                                            "Value": "Centre"
                                        },
                                        {
                                            "Name": "WndOpenSound",
                                            "Value": "0"
                                        },
                                        {
                                            "Name": "WndCloseSound",
                                            "Value": "0"
                                        },
                                        {
                                            "Name": "HexgonOverlayerColor",
                                            "Value": "1 1 1 1"
                                        },
                                        {
                                            "Name": "HexgonOverlayerImage",
                                            "Value": ""
                                        },
                                        {
                                            "Name": "HexgonSideColor",
                                            "Value": "1 1 1 1"
                                        },
                                        {
                                            "Name": "HexgonSideImage",
                                            "Value": ""
                                        },
                                        {
                                            "Name": "HexgonTopColor",
                                            "Value": "1 1 1 1"
                                        },
                                        {
                                            "Name": "HexgonTopImage",
                                            "Value": ""
                                        }
                                    ]
                                }
                            ]
                        }
                    ]
                },
                {
                    "Type": "StaticText",
                    "Name": "LotteryInfoItem-PrizeProbability",
                    "Property": [
                        {
                            "Name": "Area",
                            "Value": "{{0,0},{0,0},{0.24835,-3},{1,0}}"
                        },
                        {
                            "Name": "HorizontalAlignment",
                            "Value": "Right"
                        },
                        {
                            "Name": "Text",
                            "Value": "30%"
                        },
                        {
                            "Name": "Touchable",
                            "Value": "false"
                        },
                        {
                            "Name": "WndOpenSound",
                            "Value": "0"
                        },
                        {
                            "Name": "WndCloseSound",
                            "Value": "0"
                        },
                        {
                            "Name": "TextColor",
                            "Value": "0.188235 0.172549 0.168627 1"
                        },
                        {
                            "Name": "TextHorzAlignment",
                            "Value": "Centre"
                        },
                        {
                            "Name": "TextLineExtraSpace",
                            "Value": "0"
                        },
                        {
                            "Name": "TextVertAlignment",
                            "Value": "Centre"
                        }
                    ]
                }
            ]
        }
    }
}