{
    "actorName": "g2020_house_toy.actor",
    "base": "public_buildings_base",
    "regionCfg": "myplugin/region_public_buildings_toy",
    "regionKey": "public_buildings_toy",
    "boundingVolume": {
        "type": "Composite",
        "params": [
            {
                "type": "Box",
                "params": [
                    -6.2,
                    0,
                    -3.3,
                    0.7,
                    6,
                    2.5
                ]
            },
            {
                "type": "Box",
                "params": [
                    -0.5,
                    0,
                    -3.3,
                    0.7,
                    6,
                    4.6
                ]
            },
            {
                "type": "Box",
                "params": [
                    -6.2,
                    0,
                    -3.3,
                    -4.8,
                    6,
                    4.6
                ]
            },
            {
                "type": "Box",
                "params": [
                    -6,
                    0,
                    6.4,
                    -5.5,
                    4,
                    6.8
                ]
            },
            {
                "type": "Box",
                "params": [
                    0.5,
                    0,
                    6.4,
                    0,
                    4,
                    6.8
                ]
            },
            {
                "type": "Box",
                "params": [
                    -6.2,
                    4.1,
                    0,
                    0.7,
                    3.9,
                    7
                ]
            },
            {
                "type": "Box",
                "params": [
                    -6.2,
                    4.1,
                    6.4,
                    -5.2,
                    5.3,
                    6.9
                ]
            },
            {
                "type": "Box",
                "params": [
                    0.6,
                    4.1,
                    6.4,
                    -0.4,
                    5.3,
                    6.9
                ]
            },
            {
                "type": "Box",
                "params": [
                    -6.2,
                    6,
                    0,
                    0.7,
                    3.9,
                    4.6
                ]
            },
            {
                "type": "Box",
                "params": [
                    -6.2,
                    6,
                    -3.7,
                    0.7,
                    6.6,
                    3
                ]
            },
            {
                "type": "Box",
                "params": [
                    -6.2,
                    11.3,
                    -3.7,
                    0.7,
                    10.7,
                    3
                ]
            },
            {
                "type": "Box",
                "params": [
                    -4.2,
                    11.3,
                    -1.7,
                    -1.4,
                    11.6,
                    1
                ]
            },
            {
                "type": "Box",
                "params": [
                    -2.2,
                    11.3,
                    -2.7,
                    -2.4,
                    11.6,
                    1
                ]
            },
            {
                "type": "Box",
                "params": [
                    -6.1,
                    6,
                    -3.7,
                    -6.6,
                    11.3,
                    3
                ]
            },
            {
                "type": "Box",
                "params": [
                    1,
                    6,
                    -3.7,
                    0.6,
                    11.3,
                    3
                ]
            },
            {
                "type": "Box",
                "params": [
                    7,
                    0.3,
                    7.4,
                    -7.3,
                    0,
                    -4.8
                ]
            },
            {
                "type": "Box",
                "params": [
                    6.2,
                    4.6,
                    2.6,
                    0.8,
                    0,
                    -3.3
                ]
            },
            {
                "type": "Box",
                "params": [
                    5.4,
                    4.6,
                    1.8,
                    1.6,
                    5.8,
                    -2.5
                ]
            },
            {
                "type": "Box",
                "params": [
                    4.7,
                    10.7,
                    1.2,
                    2,
                    5.8,
                    -1.8
                ]
            },
            {
                "type": "Box",
                "params": [
                    5.1,
                    10.7,
                    0,
                    2,
                    13.6,
                    -1
                ]
            },
            {
                "type": "Box",
                "params": [
                    5.3,
                    4.6,
                    4,
                    1.8,
                    0,
                    5.6
                ]
            }
        ]
    }
}