{
	"collision": true,
    "boundingVolume": {
        "type": "Composite",
        "params": [
            {
                "type": "Box",
                "params": [
                    5,
                    1.2,
                    3
                ]
            },
            {
                "type": "Box",
                "params": [
                    -0.5,
                    1.2,
                    -1.5,
                    2.2,
                    2,
                    1.5
                ]
            }
        ]
    },
	"interactionUI":
        {
            "centerBtns":[
                {
                    "text":"item_testlang",
                    "image":"plugin/myplugin/image/hand_click.png",
                    "event": "FOOD_BUY"
                }
            ],
            "followParams":{
                "followScenePos": false
            }
        },
    "actorName": "g2020_car04.actor",
    "base": "food_base"
}