{
    "defaultBlock": "",
    "regionkey": "house03_area04",
    "defaultChildRegionBlock": [
        "",
        "",
        ""
    ],
    "childRegionKey": [
        "wallRegion",
        "floorRegion",
        "ceilingRegion"
    ],
    "wallRegion": [
        {
            "min": {
                "x": 16,
                "y": 2,
                "z": 20
            },
            "max": {
                "x": 25,
                "y": 7,
                "z": 30
            }
        }
    ],
    "floorRegion": [
        {
            "min": {
                "x": 16,
                "y": 1,
                "z": 20
            },
            "max": {
                "x": 25,
                "y": 1,
                "z": 30
            }
        }
    ],
    "ceilingRegion": [
        {
            "min": {
                "x": 16,
                "y": 8,
                "z": 20
            },
            "max": {
                "x": 25,
                "y": 8,
                "z": 30
            }
        }
    ],
    "base": "house_default_inside_map_area_base"
}