{
    "skin": {
        "body": "60"
    },
    "boundingVolume": {
        "type": "Composite",
        "params": [
            {
                "type": "Box",
                "params": [
                    -1.5,
                    0,
                    -1.5,
                    1.75,
                    2.6,
                    -0.5
                ]
            },
            {
                "type": "Box",
                "params": [
                    -1.5,
                    0,
                    -1.5,
                    -1.9,
                    1.15,
                    -0.5
                ]
            },
            {
                "type": "Box",
                "params": [
                    1,
                    0,
                    -1.5,
                    1.9,
                    2.6,
                    1.1
                ]
            },
            {
                "type": "Box",
                "params": [
                    1,
                    0,
                    1.5,
                    1.9,
                    1.3,
                    1.1
                ]
            }
        ]
    },
    "actorName": "g2020_fru_chairs4.actor",
    "base": "fur_base"
}