{
    "defaultBlock": "",
    "regionkey": "house10_area13",
    "defaultChildRegionBlock": [
        "",
        "",
        ""
    ],
    "childRegionKey": [
        "wallRegion",
        "floorRegion",
        "ceilingRegion"
    ],
    "wallRegion": [
        {
            "min": {
                "x": 102,
                "y": 71,
                "z": 153
            },
            "max": {
                "x": 129,
                "y": 88,
                "z": 179
            }
        }
    ],
    "floorRegion": [
        {
            "min": {
                "x": 102,
                "y": 70,
                "z": 153
            },
            "max": {
                "x": 129,
                "y": 70,
                "z": 179
            }
        }
    ],
    "ceilingRegion": [
        {
            "min": {
                "x": 102,
                "y": 89,
                "z": 153
            },
            "max": {
                "x": 129,
                "y": 89,
                "z": 179
            }
        }
    ],
    "base": "house_default_inside_map_area_base"
}