{
    "skyBox": {
        "texture": "myplugin/sky/Sky03",
        "rotate": {
            "x": 0,
            "y": 30,
            "z": 0
        }
    },
    "region": [],
    "entity": [
        {
            "cfg": "myplugin/doorway_school_to_map001",
            "pitch": 0,
            "pos": {
                "x": 41,
                "y": 2.1,
                "z": 22.5
            },
            "ry": 0
        }
    ],
    "mapEntry": {
        "map001": [
            "myplugin/doorway_school_to_map001"
        ]
    },
    "releaseState": "school"
}