{
    "skin": {
        "body": "1"
    },
    "name": "秋千，自己有bts",
    "actorName": "g2020_fru_qiuqian.actor",
    "ridePos": [
        {
            "yaw": 0,
            "pos": {
                "y": 0,
                "z": 0,
                "x": 0
            },
            "out": {
                "y": 0,
                "z": 0,
                "x": 0
            },
            "attachPoint": "attachPoints1",
            "ctrl": false,
            "view": false,
            "rideAction": {
                "idle" : "run"
            },
            "passengerAction": {
                "base": "sit1"
            }
        }
    ],
    "attachPoints": [
        {
            "name": "attachPoints1",
            "bone": "s_guadian_1",
            "position": {
                "y": 0,
                "z": 0,
                "x": 0
            },
            "rotation": {
                "y": 0,
                "z": 0,
                "x": 0
            },
            "scale": 1,
            "propagateScaling": false,
            "alignWorldYAxis": false,
            "matchActorOrientation": false
        }
    ],
    "interactionUI": {
        "cfgKey": "interactionUI",
        "centerBtns": [
            {
                "text": "sit",
                "image": "plugin/myplugin/image/hand_click.png",
                "event": "ENTITY_qiuqian"
            }
        ],
        "followParams": {
            "followScenePos": false
        }
    },
    "base": "fur_base"
}